gprsiot/__init__.py
gprsiot/gprsiot.py
sixfab_gprsiot-1.0.0.dist-info/DESCRIPTION.rst
sixfab_gprsiot-1.0.0.dist-info/METADATA
sixfab_gprsiot-1.0.0.dist-info/RECORD
sixfab_gprsiot-1.0.0.dist-info/WHEEL
sixfab_gprsiot-1.0.0.dist-info/metadata.json
sixfab_gprsiot-1.0.0.dist-info/top_level.txt
