Metadata-Version: 2.0
Name: sixfab-gprsiot
Version: 1.0.0
Summary: sixfab python libraries
Home-page: https://github.com/sixfab/Sixfab_RPi_GPRSIoT_HAT
Author: Yasin Kaya
Author-email: yasinkaya.121@gmail.com
License: MIT
Platform: UNKNOWN
Requires-Dist: pigpio
Requires-Dist: pyserial
